<?xml version="1.0" encoding="UTF-8"?>
<TEXTE_VERSION>
<META>
<META_COMMUN>
<ID>JORFTEXT000029837687</ID>
<ID_ELI>http://www.legifrance.gouv.fr/eli/arrete/2014/12/3/AFSR1428694A/jo/texte</ID_ELI>
<ANCIEN_ID/>
<ORIGINE>JORF</ORIGINE>
<URL>texte/version/JORF/TEXT/00/00/29/83/76/JORFTEXT000029837687.xml</URL>
<NATURE>ARRETE</NATURE>
</META_COMMUN>
<META_SPEC>
<META_TEXTE_CHRONICLE>
<CID>JORFTEXT000029837687</CID>
<NUM/>
<NUM_SEQUENCE>37</NUM_SEQUENCE>
<NOR>AFSR1428694A</NOR>
<DATE_PUBLI>2014-12-05</DATE_PUBLI>
<DATE_TEXTE>2014-12-03</DATE_TEXTE>
<ORIGINE_PUBLI>JORF n°0281 du 5 décembre 2014</ORIGINE_PUBLI>
<PAGE_DEB_PUBLI/>
<PAGE_FIN_PUBLI/>
</META_TEXTE_CHRONICLE>
<META_TEXTE_VERSION>


<TITRE>ARRÊTÉ du 3 décembre 2014</TITRE>
<TITREFULL>Arrêté du 3 décembre 2014 modifiant l'arrêté du 18 octobre 2013 portant délégation de signature (direction des ressources humaines)</TITREFULL>


<DATE_DEBUT/>
<DATE_FIN/>
<AUTORITE/>
<MINISTERE>Ministère des affaires sociales, de la santé et des droits des femmes</MINISTERE>
<MCS_TXT/>
<LIENS>
<LIEN cidtexte="JORFTEXT000000261276" datesignatexte="2005-07-27" id="JORFTEXT000000261276" naturetexte="DECRET" nortexte="PRMX0500111D" num="" numtexte="2005-850" sens="source" typelien="CITATION">Décret n°2005-850 du 27 juillet 2005 (V)</LIEN>
<LIEN cidtexte="JORFTEXT000027837846" datesignatexte="2013-08-12" id="JORFTEXT000027837846" naturetexte="DECRET" nortexte="AFSZ1318587D" num="" numtexte="2013-727" sens="source" typelien="CITATION">Décret n°2013-727  du 12 août 2013 (V)</LIEN>
</LIENS>

</META_TEXTE_VERSION>
</META_SPEC>
</META>

<VISAS>
<CONTENU>
<p align="left">
<br/>Le directeur des ressources humaines,<br/>Vu le décret n° 2005-850 du 27 juillet 2005 relatif aux délégations de signature des membres du Gouvernement ;<br/>Vu le décret n° 2013-727 du 12 août 2013 portant création, organisation et attribution d'un secrétariat général des ministères des affaires sociales ;<br/>Vu le décret du 16 octobre 2013 portant nomination du directeur des ressources humaines ;<br/>Vu l'arrêté du 12 août 2013 modifié portant organisation de la direction des ressources humaines en sous-directions et en bureaux ;<br/>Vu l'arrêté du 18 octobre 2013 modifié portant délégation de signature (direction des ressources humaines),<br/>Arrête :</p>
</CONTENU>
</VISAS>
<SIGNATAIRES>
<CONTENU>
<div align="left">
<p>Fait le 3 décembre 2014.</p>
</div>
<div align="left">
<p>J. Blondel</p>
</div>
</CONTENU>
</SIGNATAIRES>
<TP>
<CONTENU/>
</TP>

<ABRO>
<CONTENU/>
</ABRO>
<RECT>
<CONTENU/>
</RECT>
<SM>
<CONTENU/>
</SM>

</TEXTE_VERSION>
